[{"id":"page14","title":"专辑《Неясный (Experiment)》已发布","description":"音乐发布通知","published":1780531200000,"category":"电子音乐","password":false},{"id":"page13","title":"专辑《EPHEMERAL CHRØNO 2》已发布","description":"音乐发布通知","published":1780099200000,"category":"电子音乐","password":false},{"id":"page12","title":"专辑《EPHEMERAL CHRØNO》已发布","description":"音乐发布通知","published":1778889600000,"category":"电子音乐","password":false},{"id":"page11","title":"专辑《CHAOS UNIVERSE II》已发布","description":"音乐发布通知","published":1778025600000,"category":"电子音乐","password":false},{"id":"page10","title":"专辑《CHAOS UNIVERSE》已发布","description":"音乐发布通知","published":1765584000000,"category":"电子音乐","password":false},{"id":"page9","title":"乙酸钙的脱羧反应制取液态丙酮","description":"羧酸盐的脱羧反应","published":1754179200000,"category":"有机化学","password":false},{"id":"page8","title":"双草酸酯与过氧化氢在乙酸钠催化作用下的荧光盛宴","description":"有机物的催化反应","published":1752710400000,"category":"有机化学","password":false},{"id":"page7","title":"氯化铵与氢氧化钠的复分解反应制氨","description":"盐与碱的复分解反应","published":1750896000000,"category":"无机化学","password":false},{"id":"page6","title":"用化学将国窖变成一瓶无水伏特加","description":"氧化钙的脱水干燥反应","published":1750723200000,"category":"无机化学","password":false},{"id":"page5","title":"碘镁活化法制备无水乙醇","description":"利用碘-镁活化法制备无水乙醇","published":1750550400000,"category":"无机化学","password":false},{"id":"page3","title":"铜离子的变色","description":"铜离子在不同配位环境下产生的不同颜色","published":1742083200000,"category":"无机化学","password":false},{"id":"page1","title":"铝热反应","description":"铝热反应的原料，条件与反应现象","published":1741996800000,"category":"无机化学","password":false},{"id":"page2","title":"镁热反应","description":"镁热反应的原料，条件与反应现象","published":1741996800000,"category":"无机化学","password":false},{"id":"page4","title":"焰色试验","description":"不同的金属离子在离子化环境中发出不同波长的光","published":1741996800000,"category":"无机化学","password":false}]